src/axi4_slave.sv
module axi4_slave (
    input  logic        ACLK,
    input  logic        ARESETn,

    // 写地址通道
    input  logic [31:0] AWADDR,
    input  logic        AWVALID,
    output logic        AWREADY,

    // 写数据通道
    input  logic [31:0] WDATA,
    input  logic [3:0]  WSTRB,
    input  logic        WVALID,
    output logic        WREADY,

    // 写响应通道
    output logic [1:0]  BRESP,
    output logic        BVALID,
    input  logic        BREADY,

    // 读地址通道
    input  logic [31:0] ARADDR,
    input  logic        ARVALID,
    output logic        ARREADY,

    // 读数据通道
    output logic [31:0] RDATA,
    output logic [1:0]  RRESP,
    output logic        RVALID,
    input  logic        RREADY
);
    // 内部寄存器存储器 (256字)
    logic [31:0] mem [0:255];

    // 写地址、数据握手
    always_ff @(posedge ACLK or negedge ARESETn) begin
        if (!ARESETn) begin
            AWREADY <= 0;
            WREADY  <= 0;
            BVALID  <= 0;
        end else begin
            if (AWVALID && !AWREADY) AWREADY <= 1;
            else AWREADY <= 0;

            if (WVALID && !WREADY) begin
                WREADY <= 1;
                if (WSTRB[0]) mem[AWADDR[9:2]][7:0]   <= WDATA[7:0];
                if (WSTRB[1]) mem[AWADDR[9:2]][15:8]  <= WDATA[15:8];
                if (WSTRB[2]) mem[AWADDR[9:2]][23:16] <= WDATA[23:16];
                if (WSTRB[3]) mem[AWADDR[9:2]][31:24] <= WDATA[31:24];
                BVALID <= 1;
            end else begin
                WREADY <= 0;
            end

            if (BVALID && BREADY) BVALID <= 0;
        end
    end

    // 读地址、数据握手
    always_ff @(posedge ACLK or negedge ARESETn) begin
        if (!ARESETn) begin
            ARREADY <= 0;
            RVALID  <= 0;
        end else begin
            if (ARVALID && !ARREADY) begin
                ARREADY <= 1;
                RDATA   <= mem[ARADDR[9:2]];
                RVALID  <= 1;
            end else begin
                ARREADY <= 0;
            end

            if (RVALID && RREADY) RVALID <= 0;
        end
    end

    // 写响应
    assign BRESP = 2'b00; // OKAY
    assign RRESP = 2'b00; // OKAY
endmodule

src/axi4_tb.sv
module axi4_tb;
    logic        clk;
    logic        rstn;
    logic [31:0] awaddr, wdata, araddr;
    logic        awvalid, wvalid, arvalid, bready, rready;
    logic [3:0]  wstrb;
    logic        awready, wready, bvalid, arready, rvalid;
    logic [31:0] rdata;
    logic [1:0]  bresp, rresp;

    // 生成时钟信号
    always #5 clk = ~clk;

    // 实例化 AXI4 从设备
    axi4_slave dut (
        .ACLK(clk),
        .ARESETn(rstn),
        .AWADDR(awaddr),
        .AWVALID(awvalid),
        .AWREADY(awready),
        .WDATA(wdata),
        .WSTRB(wstrb),
        .WVALID(wvalid),
        .WREADY(wready),
        .BRESP(bresp),
        .BVALID(bvalid),
        .BREADY(bready),
        .ARADDR(araddr),
        .ARVALID(arvalid),
        .ARREADY(arready),
        .RDATA(rdata),
        .RRESP(rresp),
        .RVALID(rvalid),
        .RREADY(rready)
    );

    initial begin
        // 初始化
        clk = 0;
        rstn = 0;
        awvalid = 0; wvalid = 0; arvalid = 0;
        bready = 0; rready = 0;
        #20 rstn = 1;

        // 写数据测试
        #10 awaddr = 32'h00000004; awvalid = 1;
        wdata = 32'hDEADBEEF; wstrb = 4'b1111; wvalid = 1;
        #10 awvalid = 0; wvalid = 0; bready = 1;
        #10 bready = 0;

        // 读数据测试
        #10 araddr = 32'h00000004; arvalid = 1;
        #10 arvalid = 0; rready = 1;
        #10 rready = 0;

        #50 $finish;
    end

    initial begin
        $dumpfile("axi4_tb.vcd");
        $dumpvars(0, axi4_tb);
    end
endmodule

sim/axi4_tb.vcd
$date
	Wed Mar 19 09:28:54 2025
$end
$version
	Icarus Verilog
$end
$timescale
	1s
$end
$scope module axi4_tb $end
$var wire 2 ! bresp [1:0] $end
$var wire 2 " rresp [1:0] $end
$var wire 1 # wready $end
$var wire 1 $ rvalid $end
$var wire 32 % rdata [31:0] $end
$var wire 1 & bvalid $end
$var wire 1 ' awready $end
$var wire 1 ( arready $end
$var reg 32 ) araddr [31:0] $end
$var reg 1 * arvalid $end
$var reg 32 + awaddr [31:0] $end
$var reg 1 , awvalid $end
$var reg 1 - bready $end
$var reg 1 . clk $end
$var reg 1 / rready $end
$var reg 1 0 rstn $end
$var reg 32 1 wdata [31:0] $end
$var reg 4 2 wstrb [3:0] $end
$var reg 1 3 wvalid $end
$scope module dut $end
$var wire 1 . ACLK $end
$var wire 32 4 ARADDR [31:0] $end
$var wire 1 0 ARESETn $end
$var wire 1 * ARVALID $end
$var wire 32 5 AWADDR [31:0] $end
$var wire 1 , AWVALID $end
$var wire 1 - BREADY $end
$var wire 2 6 BRESP [1:0] $end
$var wire 1 / RREADY $end
$var wire 2 7 RRESP [1:0] $end
$var wire 32 8 WDATA [31:0] $end
$var wire 4 9 WSTRB [3:0] $end
$var wire 1 3 WVALID $end
$var reg 1 ( ARREADY $end
$var reg 1 ' AWREADY $end
$var reg 1 & BVALID $end
$var reg 32 : RDATA [31:0] $end
$var reg 1 $ RVALID $end
$var reg 1 # WREADY $end
$upscope $end
$upscope $end
$enddefinitions $end
#0
$dumpvars
bx :
bx 9
bx 8
b0 7
b0 6
bx 5
bx 4
03
bx 2
bx 1
00
0/
0.
0-
0,
bx +
0*
bx )
0(
0'
0&
bx %
0$
0#
b0 "
b0 !
$end
#5
1.
#10
0.
#15
1.
#20
0.
10
#25
1.
#30
0.
13
b1111 2
b1111 9
b11011110101011011011111011101111 1
b11011110101011011011111011101111 8
1,
b100 +
b100 5
#35
1&
1#
1'
1.
#40
0.
1-
03
0,
#45
0&
0#
0'
1.
#50
0.
0-
#55
1.
#60
0.
1*
b100 )
b100 4
#65
1$
b11011110101011011011111011101111 %
b11011110101011011011111011101111 :
1(
1.
#70
0.
1/
0*
#75
0$
0(
1.
#80
0.
0/
